helium_positioning_api/DataObjects.py
helium_positioning_api/__init__.py
helium_positioning_api/__main__.py
helium_positioning_api/api.py
helium_positioning_api/auxilary.py
helium_positioning_api/distance_prediction.py
helium_positioning_api/midpoint.py
helium_positioning_api/nearest_neighbor.py
helium_positioning_api/py.typed
helium_positioning_api/trilateration.py
helium_positioning_api-0.0.2.dev1683125793.dist-info/METADATA
helium_positioning_api-0.0.2.dev1683125793.dist-info/WHEEL
helium_positioning_api-0.0.2.dev1683125793.dist-info/LICENSE
helium_positioning_api-0.0.2.dev1683125793.dist-info/RECORD
