Metadata-Version: 2.1
Name: helium-positioning-api
Version: 0.0.2.dev1683125793
Summary: Helium Positioning API
Home-page: https://github.com/emergotechnologies/helium-positioning-api
License: MIT
Author: Lukas Huber
Author-email: lukas.huber@fh-kufstein.ac.at
Requires-Python: >=3.8,<4.0
Classifier: Development Status :: 3 - Alpha
Classifier: License :: OSI Approved :: MIT License
Classifier: Programming Language :: Python :: 3
Classifier: Programming Language :: Python :: 3.8
Classifier: Programming Language :: Python :: 3.9
Classifier: Programming Language :: Python :: 3.10
Classifier: Programming Language :: Python :: 3.11
Requires-Dist: click (>=8.0.1)
Requires-Dist: fastapi (>=0.87.0,<0.88.0)
Requires-Dist: haversine (>=2.7.0,<3.0.0)
Requires-Dist: helium-api-wrapper (>=0.0.1.dev1675239484,<0.0.2)
Requires-Dist: joblib (>=1.2.0,<2.0.0)
Requires-Dist: pandas (>=1.5.3,<2.0.0)
Requires-Dist: pydantic (>=1.10.2,<2.0.0)
Requires-Dist: pytest-mock (>=3.10.0,<4.0.0)
Requires-Dist: python-dotenv (>=0.21.1,<0.22.0)
Requires-Dist: scikit-learn (==1.0.2)
Requires-Dist: utm (>=0.7.0,<0.8.0)
Requires-Dist: uvicorn (>=0.19.0,<0.20.0)
Project-URL: Changelog, https://github.com/emergotechnologies/helium-positioning-apireleases
Project-URL: Documentation, https://helium-positioning-api.readthedocs.io
Project-URL: Repository, https://github.com/emergotechnologies/helium-positioning-api
